<annotation verified="no">
  <folder>image5</folder>
  <filename>image3337</filename>
  <path>/home/tufail/Desktop/image5/image3337.jpg</path>
  <source>
    <database>Unknown</database>
  </source>
  <size>
    <width>1920</width>
    <height>1080</height>
    <depth>3</depth>
  </size>
  <segmented>0</segmented>
  <object>
    <type>robndbox</type>
    <name>gun</name>
    <pose>Unspecified</pose>
    <truncated>0</truncated>
    <difficult>0</difficult>
    <robndbox>
      <cx>508.7628</cx>
      <cy>542.5847</cy>
      <w>988.0152</w>
      <h>453.577</h>
      <angle>3.078645</angle>
    </robndbox>
  </object>
</annotation>
