<annotation verified="no">
  <folder>image4</folder>
  <filename>image2117</filename>
  <path>/home/tufail/Desktop/image4/image2117.jpg</path>
  <source>
    <database>Unknown</database>
  </source>
  <size>
    <width>1280</width>
    <height>534</height>
    <depth>3</depth>
  </size>
  <segmented>0</segmented>
  <object>
    <type>robndbox</type>
    <name>pistol</name>
    <pose>Unspecified</pose>
    <truncated>0</truncated>
    <difficult>0</difficult>
    <robndbox>
      <cx>699.556</cx>
      <cy>181.4968</cy>
      <w>162.8558</w>
      <h>254.4229</h>
      <angle>0.62366</angle>
    </robndbox>
  </object>
  <object>
    <type>robndbox</type>
    <name>gun</name>
    <pose>Unspecified</pose>
    <truncated>0</truncated>
    <difficult>0</difficult>
    <robndbox>
      <cx>1059.4067</cx>
      <cy>325.3225</cy>
      <w>53.9488</w>
      <h>412.8739</h>
      <angle>0.229565</angle>
    </robndbox>
  </object>
</annotation>
