<annotation verified="no">
  <folder>image3</folder>
  <filename>image1257</filename>
  <path>/home/tufail/Desktop/image3/image1257.jpg</path>
  <source>
    <database>Unknown</database>
  </source>
  <size>
    <width>1000</width>
    <height>563</height>
    <depth>3</depth>
  </size>
  <segmented>0</segmented>
  <object>
    <type>robndbox</type>
    <name>pistol</name>
    <pose>Unspecified</pose>
    <truncated>0</truncated>
    <difficult>0</difficult>
    <robndbox>
      <cx>737.4065</cx>
      <cy>291.3575</cy>
      <w>316.175</w>
      <h>171.7591</h>
      <angle>2.653844</angle>
    </robndbox>
  </object>
</annotation>
