<annotation verified="no">
  <folder>image4</folder>
  <filename>image2227</filename>
  <path>/home/tufail/Desktop/image4/image2227.jpg</path>
  <source>
    <database>Unknown</database>
  </source>
  <size>
    <width>630</width>
    <height>420</height>
    <depth>3</depth>
  </size>
  <segmented>0</segmented>
  <object>
    <type>robndbox</type>
    <name>gun</name>
    <pose>Unspecified</pose>
    <truncated>0</truncated>
    <difficult>0</difficult>
    <robndbox>
      <cx>356.2597</cx>
      <cy>172.7977</cy>
      <w>199.2514</w>
      <h>164.834</h>
      <angle>0.178811</angle>
    </robndbox>
  </object>
</annotation>
