<annotation verified="no">
  <folder>image4</folder>
  <filename>image2706</filename>
  <path>/home/tufail/Desktop/image4/image2706.jpg</path>
  <source>
    <database>Unknown</database>
  </source>
  <size>
    <width>640</width>
    <height>274</height>
    <depth>3</depth>
  </size>
  <segmented>0</segmented>
  <object>
    <type>robndbox</type>
    <name>pistol</name>
    <pose>Unspecified</pose>
    <truncated>0</truncated>
    <difficult>0</difficult>
    <robndbox>
      <cx>307.8186</cx>
      <cy>235.0569</cy>
      <w>74.2668</w>
      <h>38.8544</h>
      <angle>0.325177</angle>
    </robndbox>
  </object>
</annotation>
