<annotation verified="no">
  <folder>image5</folder>
  <filename>image3297</filename>
  <path>/home/tufail/Desktop/image5/image3297.jpg</path>
  <source>
    <database>Unknown</database>
  </source>
  <size>
    <width>1920</width>
    <height>1080</height>
    <depth>3</depth>
  </size>
  <segmented>0</segmented>
  <object>
    <type>robndbox</type>
    <name>gun</name>
    <pose>Unspecified</pose>
    <truncated>0</truncated>
    <difficult>0</difficult>
    <robndbox>
      <cx>812.6236</cx>
      <cy>392.0</cy>
      <w>93.6583</w>
      <h>783.951</h>
      <angle>0.237288</angle>
    </robndbox>
  </object>
</annotation>
