<annotation verified="no">
  <folder>weapon_training</folder>
  <filename>image542</filename>
  <path>/home/tufail/Desktop/weapon_training/image542.jpg</path>
  <source>
    <database>Unknown</database>
  </source>
  <size>
    <width>268</width>
    <height>188</height>
    <depth>3</depth>
  </size>
  <segmented>0</segmented>
  <object>
    <type>robndbox</type>
    <name>pistol</name>
    <pose>Unspecified</pose>
    <truncated>0</truncated>
    <difficult>0</difficult>
    <robndbox>
      <cx>229.8261</cx>
      <cy>47.3179</cy>
      <w>70.0219</w>
      <h>33.7329</h>
      <angle>2.931593</angle>
    </robndbox>
  </object>
</annotation>
