<annotation verified="no">
  <folder>image3</folder>
  <filename>image1037</filename>
  <path>/home/tufail/Desktop/image3/image1037.jpg</path>
  <source>
    <database>Unknown</database>
  </source>
  <size>
    <width>620</width>
    <height>310</height>
    <depth>3</depth>
  </size>
  <segmented>0</segmented>
  <object>
    <type>robndbox</type>
    <name>pistol</name>
    <pose>Unspecified</pose>
    <truncated>0</truncated>
    <difficult>0</difficult>
    <robndbox>
      <cx>494.2417</cx>
      <cy>192.1325</cy>
      <w>131.0</w>
      <h>112.0</h>
      <angle>0.0</angle>
    </robndbox>
  </object>
</annotation>
