<annotation verified="no">
  <folder>image3</folder>
  <filename>image1384</filename>
  <path>/home/tufail/Desktop/image3/image1384.jpg</path>
  <source>
    <database>Unknown</database>
  </source>
  <size>
    <width>800</width>
    <height>450</height>
    <depth>3</depth>
  </size>
  <segmented>0</segmented>
  <object>
    <type>robndbox</type>
    <name>gun</name>
    <pose>Unspecified</pose>
    <truncated>0</truncated>
    <difficult>0</difficult>
    <robndbox>
      <cx>208.9886</cx>
      <cy>237.4785</cy>
      <w>141.8395</w>
      <h>323.5561</h>
      <angle>2.874447</angle>
    </robndbox>
  </object>
</annotation>
