<annotation verified="no">
  <folder>image3</folder>
  <filename>image1401</filename>
  <path>/home/tufail/Desktop/image3/image1401.jpg</path>
  <source>
    <database>Unknown</database>
  </source>
  <size>
    <width>2000</width>
    <height>1000</height>
    <depth>3</depth>
  </size>
  <segmented>0</segmented>
  <object>
    <type>robndbox</type>
    <name>gun</name>
    <pose>Unspecified</pose>
    <truncated>0</truncated>
    <difficult>0</difficult>
    <robndbox>
      <cx>1710.8762</cx>
      <cy>503.45</cy>
      <w>496.2524</w>
      <h>972.009</h>
      <angle>0.042761</angle>
    </robndbox>
  </object>
  <object>
    <type>robndbox</type>
    <name>gun</name>
    <pose>Unspecified</pose>
    <truncated>0</truncated>
    <difficult>0</difficult>
    <robndbox>
      <cx>264.634</cx>
      <cy>499.5005</cy>
      <w>207.3803</w>
      <h>976.9732</h>
      <angle>2.861549</angle>
    </robndbox>
  </object>
</annotation>
