<annotation verified="no">
  <folder>image5</folder>
  <filename>image3331</filename>
  <path>/home/tufail/Desktop/image5/image3331.jpg</path>
  <source>
    <database>Unknown</database>
  </source>
  <size>
    <width>1920</width>
    <height>1080</height>
    <depth>3</depth>
  </size>
  <segmented>0</segmented>
  <object>
    <type>robndbox</type>
    <name>gun</name>
    <pose>Unspecified</pose>
    <truncated>0</truncated>
    <difficult>0</difficult>
    <robndbox>
      <cx>925.0655</cx>
      <cy>557.4038</cy>
      <w>775.9089</w>
      <h>235.9892</h>
      <angle>0.522619</angle>
    </robndbox>
  </object>
  <object>
    <type>robndbox</type>
    <name>pistol</name>
    <pose>Unspecified</pose>
    <truncated>0</truncated>
    <difficult>0</difficult>
    <robndbox>
      <cx>540.0</cx>
      <cy>846.0</cy>
      <w>118.6087</w>
      <h>189.3884</h>
      <angle>0.213227</angle>
    </robndbox>
  </object>
</annotation>
