<annotation verified="no">
  <folder>weapon_training</folder>
  <filename>image20</filename>
  <path>/home/tufail/Desktop/weapon_training/image20.jpg</path>
  <source>
    <database>Unknown</database>
  </source>
  <size>
    <width>610</width>
    <height>411</height>
    <depth>3</depth>
  </size>
  <segmented>0</segmented>
  <object>
    <type>robndbox</type>
    <name>pistol</name>
    <pose>Unspecified</pose>
    <truncated>0</truncated>
    <difficult>0</difficult>
    <robndbox>
      <cx>178.463</cx>
      <cy>251.3333</cy>
      <w>94.0245</w>
      <h>28.45</h>
      <angle>0.68</angle>
    </robndbox>
  </object>
</annotation>
