<annotation verified="no">
  <folder>image3</folder>
  <filename>image1264</filename>
  <path>/home/tufail/Desktop/image3/image1264.jpg</path>
  <source>
    <database>Unknown</database>
  </source>
  <size>
    <width>634</width>
    <height>641</height>
    <depth>3</depth>
  </size>
  <segmented>0</segmented>
  <object>
    <type>robndbox</type>
    <name>pistol</name>
    <pose>Unspecified</pose>
    <truncated>0</truncated>
    <difficult>0</difficult>
    <robndbox>
      <cx>529.0241</cx>
      <cy>199.2031</cy>
      <w>106.1808</w>
      <h>112.2686</h>
      <angle>2.979492</angle>
    </robndbox>
  </object>
</annotation>
