<annotation verified="no">
  <folder>image4</folder>
  <filename>image2610</filename>
  <path>/home/tufail/Desktop/image4/image2610.jpg</path>
  <source>
    <database>Unknown</database>
  </source>
  <size>
    <width>600</width>
    <height>450</height>
    <depth>3</depth>
  </size>
  <segmented>0</segmented>
  <object>
    <type>robndbox</type>
    <name>gun</name>
    <pose>Unspecified</pose>
    <truncated>0</truncated>
    <difficult>0</difficult>
    <robndbox>
      <cx>390.2489</cx>
      <cy>261.3902</cy>
      <w>193.2263</w>
      <h>136.4132</h>
      <angle>3.072002</angle>
    </robndbox>
  </object>
</annotation>
