<annotation verified="no">
  <folder>image4</folder>
  <filename>image2783</filename>
  <path>/home/tufail/Desktop/image4/image2783.jpg</path>
  <source>
    <database>Unknown</database>
  </source>
  <size>
    <width>3840</width>
    <height>2160</height>
    <depth>3</depth>
  </size>
  <segmented>0</segmented>
  <object>
    <type>robndbox</type>
    <name>pistol</name>
    <pose>Unspecified</pose>
    <truncated>0</truncated>
    <difficult>0</difficult>
    <robndbox>
      <cx>1508.1604</cx>
      <cy>1030.7601</cy>
      <w>639.0504</w>
      <h>675.9164</h>
      <angle>0.238623</angle>
    </robndbox>
  </object>
</annotation>
