<annotation verified="no">
  <folder>image4</folder>
  <filename>image2708</filename>
  <path>/home/tufail/Desktop/image4/image2708.jpg</path>
  <source>
    <database>Unknown</database>
  </source>
  <size>
    <width>640</width>
    <height>274</height>
    <depth>3</depth>
  </size>
  <segmented>0</segmented>
  <object>
    <type>robndbox</type>
    <name>pistol</name>
    <pose>Unspecified</pose>
    <truncated>0</truncated>
    <difficult>0</difficult>
    <robndbox>
      <cx>225.8617</cx>
      <cy>195.203</cy>
      <w>32.2985</w>
      <h>97.8355</h>
      <angle>2.889497</angle>
    </robndbox>
  </object>
</annotation>
