<annotation verified="no">
  <folder>image4</folder>
  <filename>image2374</filename>
  <path>/home/tufail/Desktop/image4/image2374.jpg</path>
  <source>
    <database>Unknown</database>
  </source>
  <size>
    <width>299</width>
    <height>169</height>
    <depth>3</depth>
  </size>
  <segmented>0</segmented>
  <object>
    <type>robndbox</type>
    <name>gun</name>
    <pose>Unspecified</pose>
    <truncated>0</truncated>
    <difficult>0</difficult>
    <robndbox>
      <cx>95.0618</cx>
      <cy>92.7675</cy>
      <w>186.0</w>
      <h>48.0</h>
      <angle>3.032378</angle>
    </robndbox>
  </object>
</annotation>
