<annotation verified="no">
  <folder>weapon_training</folder>
  <filename>image547</filename>
  <path>/home/tufail/Desktop/weapon_training/image547.jpg</path>
  <source>
    <database>Unknown</database>
  </source>
  <size>
    <width>296</width>
    <height>170</height>
    <depth>3</depth>
  </size>
  <segmented>0</segmented>
  <object>
    <type>robndbox</type>
    <name>pistol</name>
    <pose>Unspecified</pose>
    <truncated>0</truncated>
    <difficult>0</difficult>
    <robndbox>
      <cx>129.5693</cx>
      <cy>122.4677</cy>
      <w>55.108</w>
      <h>38.9386</h>
      <angle>2.241593</angle>
    </robndbox>
  </object>
</annotation>
