<annotation verified="no">
  <folder>image2</folder>
  <filename>image491</filename>
  <path>/home/tufail/Desktop/image2/image491.jpg</path>
  <source>
    <database>Unknown</database>
  </source>
  <size>
    <width>275</width>
    <height>183</height>
    <depth>3</depth>
  </size>
  <segmented>0</segmented>
  <object>
    <type>robndbox</type>
    <name>pistol</name>
    <pose>Unspecified</pose>
    <truncated>0</truncated>
    <difficult>0</difficult>
    <robndbox>
      <cx>135.1701</cx>
      <cy>94.6393</cy>
      <w>229.0</w>
      <h>165.0</h>
      <angle>0.0</angle>
    </robndbox>
  </object>
</annotation>
