<annotation verified="no">
  <folder>image2</folder>
  <filename>image1160</filename>
  <path>/home/tufail/Desktop/image2/image1160.jpg</path>
  <source>
    <database>Unknown</database>
  </source>
  <size>
    <width>268</width>
    <height>188</height>
    <depth>1</depth>
  </size>
  <segmented>0</segmented>
  <object>
    <type>robndbox</type>
    <name>gun</name>
    <pose>Unspecified</pose>
    <truncated>0</truncated>
    <difficult>0</difficult>
    <robndbox>
      <cx>128.862</cx>
      <cy>85.1677</cy>
      <w>248.8354</w>
      <h>59.4468</h>
      <angle>0.344364</angle>
    </robndbox>
  </object>
</annotation>
