<annotation verified="no">
  <folder>image2</folder>
  <filename>image1066</filename>
  <path>/home/tufail/Desktop/image2/image1066.jpg</path>
  <source>
    <database>Unknown</database>
  </source>
  <size>
    <width>275</width>
    <height>183</height>
    <depth>3</depth>
  </size>
  <segmented>0</segmented>
  <object>
    <type>robndbox</type>
    <name>gun</name>
    <pose>Unspecified</pose>
    <truncated>0</truncated>
    <difficult>0</difficult>
    <robndbox>
      <cx>137.1179</cx>
      <cy>91.5153</cy>
      <w>239.5287</w>
      <h>63.1645</h>
      <angle>2.619292</angle>
    </robndbox>
  </object>
</annotation>
