<annotation verified="no">
  <folder>image2</folder>
  <filename>image931</filename>
  <path>/home/tufail/Desktop/image2/image931.jpg</path>
  <source>
    <database>Unknown</database>
  </source>
  <size>
    <width>580</width>
    <height>459</height>
    <depth>3</depth>
  </size>
  <segmented>0</segmented>
  <object>
    <type>robndbox</type>
    <name>gun</name>
    <pose>Unspecified</pose>
    <truncated>0</truncated>
    <difficult>0</difficult>
    <robndbox>
      <cx>291.1401</cx>
      <cy>212.5424</cy>
      <w>517.679</w>
      <h>305.1905</h>
      <angle>2.889183</angle>
    </robndbox>
  </object>
</annotation>
