<annotation verified="no">
  <folder>image2</folder>
  <filename>image636</filename>
  <path>/home/tufail/Desktop/image2/image636.jpg</path>
  <source>
    <database>Unknown</database>
  </source>
  <size>
    <width>275</width>
    <height>183</height>
    <depth>3</depth>
  </size>
  <segmented>0</segmented>
  <object>
    <type>robndbox</type>
    <name>pistol</name>
    <pose>Unspecified</pose>
    <truncated>0</truncated>
    <difficult>0</difficult>
    <robndbox>
      <cx>132.7029</cx>
      <cy>91.9369</cy>
      <w>222.1002</w>
      <h>150.4463</h>
      <angle>3.127346</angle>
    </robndbox>
  </object>
</annotation>
