<annotation verified="no">
  <folder>image2</folder>
  <filename>image510</filename>
  <path>/home/tufail/Desktop/image2/image510.jpg</path>
  <source>
    <database>Unknown</database>
  </source>
  <size>
    <width>225</width>
    <height>225</height>
    <depth>3</depth>
  </size>
  <segmented>0</segmented>
  <object>
    <type>robndbox</type>
    <name>pistol</name>
    <pose>Unspecified</pose>
    <truncated>0</truncated>
    <difficult>0</difficult>
    <robndbox>
      <cx>121.5907</cx>
      <cy>112.6142</cy>
      <w>167.7586</w>
      <h>119.342</h>
      <angle>2.489048</angle>
    </robndbox>
  </object>
</annotation>
