<annotation verified="no">
  <folder>image2</folder>
  <filename>image102</filename>
  <path>/home/tufail/Desktop/image2/image102.jpg</path>
  <source>
    <database>Unknown</database>
  </source>
  <size>
    <width>480</width>
    <height>360</height>
    <depth>3</depth>
  </size>
  <segmented>0</segmented>
  <object>
    <type>robndbox</type>
    <name>pistol</name>
    <pose>Unspecified</pose>
    <truncated>0</truncated>
    <difficult>0</difficult>
    <robndbox>
      <cx>238.51</cx>
      <cy>194.4584</cy>
      <w>432.9207</w>
      <h>190.1448</h>
      <angle>2.783212</angle>
    </robndbox>
  </object>
</annotation>
