<annotation verified="no">
  <folder>image2</folder>
  <filename>image326</filename>
  <path>/home/tufail/Desktop/image2/image326.jpg</path>
  <source>
    <database>Unknown</database>
  </source>
  <size>
    <width>1021</width>
    <height>640</height>
    <depth>3</depth>
  </size>
  <segmented>0</segmented>
  <object>
    <type>robndbox</type>
    <name>pistol</name>
    <pose>Unspecified</pose>
    <truncated>0</truncated>
    <difficult>0</difficult>
    <robndbox>
      <cx>478.8601</cx>
      <cy>330.3028</cy>
      <w>530.1447</w>
      <h>330.6268</h>
      <angle>2.401429</angle>
    </robndbox>
  </object>
</annotation>
