<annotation verified="no">
  <folder>image2</folder>
  <filename>image861</filename>
  <path>/home/tufail/Desktop/image2/image861.jpg</path>
  <source>
    <database>Unknown</database>
  </source>
  <size>
    <width>860</width>
    <height>465</height>
    <depth>3</depth>
  </size>
  <segmented>0</segmented>
  <object>
    <type>robndbox</type>
    <name>gun</name>
    <pose>Unspecified</pose>
    <truncated>0</truncated>
    <difficult>0</difficult>
    <robndbox>
      <cx>424.9408</cx>
      <cy>337.8697</cy>
      <w>808.4257</w>
      <h>230.2024</h>
      <angle>0.019704</angle>
    </robndbox>
  </object>
  <object>
    <type>robndbox</type>
    <name>gun</name>
    <pose>Unspecified</pose>
    <truncated>0</truncated>
    <difficult>0</difficult>
    <robndbox>
      <cx>399.6214</cx>
      <cy>116.8566</cy>
      <w>731.7924</w>
      <h>227.9807</h>
      <angle>3.139041</angle>
    </robndbox>
  </object>
</annotation>
