<annotation verified="no">
  <folder>1</folder>
  <filename>pic538</filename>
  <path>/home/tufail/Desktop/tufail/1/pic538.jpg</path>
  <source>
    <database>Unknown</database>
  </source>
  <size>
    <width>426</width>
    <height>240</height>
    <depth>3</depth>
  </size>
  <segmented>0</segmented>
  <object>
    <type>robndbox</type>
    <name>gun</name>
    <pose>Unspecified</pose>
    <truncated>0</truncated>
    <difficult>0</difficult>
    <robndbox>
      <cx>124.8514</cx>
      <cy>45.8815</cy>
      <w>73.0339</w>
      <h>36.9379</h>
      <angle>0.281454</angle>
    </robndbox>
  </object>
  <object>
    <type>robndbox</type>
    <name>gun</name>
    <pose>Unspecified</pose>
    <truncated>0</truncated>
    <difficult>0</difficult>
    <robndbox>
      <cx>252.8514</cx>
      <cy>119.8815</cy>
      <w>73.0339</w>
      <h>36.9379</h>
      <angle>2.897876</angle>
    </robndbox>
  </object>
</annotation>
