<annotation verified="no">
  <folder>1</folder>
  <filename>pic782</filename>
  <path>/home/tufail/Desktop/tufail/1/pic782.jpg</path>
  <source>
    <database>Unknown</database>
  </source>
  <size>
    <width>426</width>
    <height>240</height>
    <depth>3</depth>
  </size>
  <segmented>0</segmented>
  <object>
    <type>robndbox</type>
    <name>gun</name>
    <pose>Unspecified</pose>
    <truncated>0</truncated>
    <difficult>0</difficult>
    <robndbox>
      <cx>288.3685</cx>
      <cy>152.2733</cy>
      <w>58.8578</w>
      <h>109.2141</h>
      <angle>2.404171</angle>
    </robndbox>
  </object>
</annotation>
