<annotation verified="no">
  <folder>1</folder>
  <filename>pic768</filename>
  <path>/home/tufail/Desktop/tufail/1/pic768.jpg</path>
  <source>
    <database>Unknown</database>
  </source>
  <size>
    <width>426</width>
    <height>240</height>
    <depth>3</depth>
  </size>
  <segmented>0</segmented>
  <object>
    <type>robndbox</type>
    <name>gun</name>
    <pose>Unspecified</pose>
    <truncated>0</truncated>
    <difficult>0</difficult>
    <robndbox>
      <cx>309.3019</cx>
      <cy>134.4811</cy>
      <w>144.0</w>
      <h>110.0</h>
      <angle>0.0</angle>
    </robndbox>
  </object>
</annotation>
