<annotation verified="no">
  <folder>1</folder>
  <filename>pic836</filename>
  <path>/home/tufail/Desktop/tufail/1/pic836.jpg</path>
  <source>
    <database>Unknown</database>
  </source>
  <size>
    <width>426</width>
    <height>240</height>
    <depth>3</depth>
  </size>
  <segmented>0</segmented>
  <object>
    <type>robndbox</type>
    <name>gun</name>
    <pose>Unspecified</pose>
    <truncated>0</truncated>
    <difficult>0</difficult>
    <robndbox>
      <cx>278.6632</cx>
      <cy>51.4503</cy>
      <w>164.8106</w>
      <h>41.5078</h>
      <angle>3.072686</angle>
    </robndbox>
  </object>
</annotation>
