<annotation verified="no">
  <folder>weapon_data_1</folder>
  <filename>W1055</filename>
  <path>/home/tufail/Desktop/weapon_data_1/W1055.jpg</path>
  <source>
    <database>Unknown</database>
  </source>
  <size>
    <width>329</width>
    <height>329</height>
    <depth>3</depth>
  </size>
  <segmented>0</segmented>
  <object>
    <type>robndbox</type>
    <name>pistol</name>
    <pose>Unspecified</pose>
    <truncated>0</truncated>
    <difficult>0</difficult>
    <robndbox>
      <cx>237.9565</cx>
      <cy>52.5087</cy>
      <w>178.2975</w>
      <h>60.4956</h>
      <angle>0.04</angle>
    </robndbox>
  </object>
  <object>
    <type>robndbox</type>
    <name>pistol</name>
    <pose>Unspecified</pose>
    <truncated>0</truncated>
    <difficult>0</difficult>
    <robndbox>
      <cx>145.9291</cx>
      <cy>154.6515</cy>
      <w>237.9824</w>
      <h>144.495</h>
      <angle>0.03</angle>
    </robndbox>
  </object>
  <object>
    <type>robndbox</type>
    <name>pistol</name>
    <pose>Unspecified</pose>
    <truncated>0</truncated>
    <difficult>0</difficult>
    <robndbox>
      <cx>65.8243</cx>
      <cy>226.7973</cy>
      <w>128.0</w>
      <h>165.0</h>
      <angle>0.01</angle>
    </robndbox>
  </object>
</annotation>
