<annotation verified="no">
  <folder>weapon_data_1</folder>
  <filename>W1076</filename>
  <path>/home/tufail/Desktop/weapon_data_1/W1076.jpg</path>
  <source>
    <database>Unknown</database>
  </source>
  <size>
    <width>800</width>
    <height>533</height>
    <depth>3</depth>
  </size>
  <segmented>0</segmented>
  <object>
    <type>robndbox</type>
    <name>pistol</name>
    <pose>Unspecified</pose>
    <truncated>0</truncated>
    <difficult>0</difficult>
    <robndbox>
      <cx>262.1681</cx>
      <cy>194.395</cy>
      <w>272.0805</w>
      <h>261.0025</h>
      <angle>2.901593</angle>
    </robndbox>
  </object>
</annotation>
