<annotation verified="no">
  <folder>weapon_data_1</folder>
  <filename>W124</filename>
  <path>/home/tufail/Desktop/weapon_data_1/W124.jpg</path>
  <source>
    <database>Unknown</database>
  </source>
  <size>
    <width>306</width>
    <height>165</height>
    <depth>3</depth>
  </size>
  <segmented>0</segmented>
  <object>
    <type>robndbox</type>
    <name>pistol</name>
    <pose>Unspecified</pose>
    <truncated>0</truncated>
    <difficult>0</difficult>
    <robndbox>
      <cx>125.1609</cx>
      <cy>66.7331</cy>
      <w>20.5517</w>
      <h>18.3833</h>
      <angle>3.081593</angle>
    </robndbox>
  </object>
</annotation>
