<annotation verified="no">
  <folder>weapon_data_1</folder>
  <filename>W307</filename>
  <path>/home/tufail/Desktop/weapon_data_1/W307.jpg</path>
  <source>
    <database>Unknown</database>
  </source>
  <size>
    <width>163</width>
    <height>309</height>
    <depth>3</depth>
  </size>
  <segmented>0</segmented>
  <object>
    <type>robndbox</type>
    <name>pistol</name>
    <pose>Unspecified</pose>
    <truncated>0</truncated>
    <difficult>0</difficult>
    <robndbox>
      <cx>26.9119</cx>
      <cy>102.4488</cy>
      <w>34.1549</w>
      <h>14.4759</h>
      <angle>2.491593</angle>
    </robndbox>
  </object>
</annotation>
