<annotation verified="no">
  <folder>weapon_data_1</folder>
  <filename>W71</filename>
  <path>/home/tufail/Desktop/weapon_data_1/W71.jpg</path>
  <source>
    <database>Unknown</database>
  </source>
  <size>
    <width>275</width>
    <height>183</height>
    <depth>3</depth>
  </size>
  <segmented>0</segmented>
  <object>
    <type>robndbox</type>
    <name>pistol</name>
    <pose>Unspecified</pose>
    <truncated>0</truncated>
    <difficult>0</difficult>
    <robndbox>
      <cx>146.7241</cx>
      <cy>59.3818</cy>
      <w>84.1594</w>
      <h>34.9893</h>
      <angle>3.001593</angle>
    </robndbox>
  </object>
</annotation>
