<annotation verified="no">
  <folder>weapon_data_1</folder>
  <filename>W922</filename>
  <path>/home/tufail/Desktop/weapon_data_1/W922.jpg</path>
  <source>
    <database>Unknown</database>
  </source>
  <size>
    <width>600</width>
    <height>315</height>
    <depth>3</depth>
  </size>
  <segmented>0</segmented>
  <object>
    <type>robndbox</type>
    <name>pistol</name>
    <pose>Unspecified</pose>
    <truncated>0</truncated>
    <difficult>0</difficult>
    <robndbox>
      <cx>200.3111</cx>
      <cy>162.1569</cy>
      <w>78.7596</w>
      <h>142.1084</h>
      <angle>2.731593</angle>
    </robndbox>
  </object>
  <object>
    <type>robndbox</type>
    <name>pistol</name>
    <pose>Unspecified</pose>
    <truncated>0</truncated>
    <difficult>0</difficult>
    <robndbox>
      <cx>394.75</cx>
      <cy>237.125</cy>
      <w>47.0912</w>
      <h>89.6182</h>
      <angle>2.261593</angle>
    </robndbox>
  </object>
</annotation>
